component_generator/__init__.py
component_generator/__main__.py
component_generator/cli.py
component_generator/constants.py
component_generator/generate.py
component_generator/helpers.py
component_generator/info_file.py
component_generator/component_files/component.py
component_generator/component_files/consumer.py
component_generator/component_files/service.py
component_generator-0.0.0.dist-info/AUTHORS.rst
component_generator-0.0.0.dist-info/LICENSE
component_generator-0.0.0.dist-info/METADATA
component_generator-0.0.0.dist-info/WHEEL
component_generator-0.0.0.dist-info/entry_points.txt
component_generator-0.0.0.dist-info/top_level.txt
component_generator-0.0.0.dist-info/RECORD
