Metadata-Version: 2.1
Name: component-generator
Version: 0.0.0
Summary: Generate backend components quickly
Home-page: https://github.com/onna/python-component-generator
Author: Darren Buttigieg
Author-email: darren@onna.com
License: BSD-2-Clause
Project-URL: Documentation, https://python-component-generator.readthedocs.io/
Project-URL: Changelog, https://python-component-generator.readthedocs.io/en/latest/changelog.html
Project-URL: Issue Tracker, https://github.com/onna/python-component-generator/issues
Platform: UNKNOWN
Classifier: Development Status :: 5 - Production/Stable
Classifier: Intended Audience :: Developers
Classifier: License :: OSI Approved :: BSD License
Classifier: Operating System :: Unix
Classifier: Operating System :: POSIX
Classifier: Operating System :: Microsoft :: Windows
Classifier: Programming Language :: Python
Classifier: Programming Language :: Python :: 3
Classifier: Programming Language :: Python :: 3 :: Only
Classifier: Programming Language :: Python :: 3.6
Classifier: Programming Language :: Python :: 3.7
Classifier: Programming Language :: Python :: 3.8
Classifier: Programming Language :: Python :: 3.9
Classifier: Programming Language :: Python :: Implementation :: CPython
Classifier: Programming Language :: Python :: Implementation :: PyPy
Classifier: Topic :: Utilities
Requires-Python: >=3.6
